paddle_bfloat.cpython-38-powerpc64le-linux-gnu.so
paddle_bfloat-0.1.7.dist-info/top_level.txt
paddle_bfloat-0.1.7.dist-info/RECORD
paddle_bfloat-0.1.7.dist-info/LICENSE.txt
paddle_bfloat-0.1.7.dist-info/METADATA
paddle_bfloat-0.1.7.dist-info/WHEEL
